LICENSE
MANIFEST.in
README
README.markdown
setup.py
docs/Makefile
docs/conf.py
docs/contributing.rst
docs/dummy-settings.py
docs/exceptions.rst
docs/forms.rst
docs/handling_requests.rst
docs/index.rst
docs/loaders.rst
docs/make.bat
docs/signals.rst
docs/templatetags.rst
docs/utilities.rst
docs/validators.rst
docs/what.rst
docs/_ext/djangodocs.py
docs/_ext/philodocs.py
docs/cla/ithinksw-ccla.txt
docs/cla/ithinksw-icla.txt
docs/contrib/intro.rst
docs/contrib/penfield.rst
docs/contrib/shipherd.rst
docs/contrib/sobol.rst
docs/contrib/waldo.rst
docs/contrib/winer.rst
docs/models/collections.rst
docs/models/entities.rst
docs/models/fields.rst
docs/models/intro.rst
docs/models/miscellaneous.rst
docs/models/nodes-and-views.rst
docs/releases/0.9.1.rst
docs/releases/0.9.2.rst
docs/tutorials/getting-started.rst
docs/tutorials/intro.rst
docs/tutorials/shipherd.rst
philo/__init__.py
philo/exceptions.py
philo/middleware.py
philo/signals.py
philo/tests.py
philo/urls.py
philo/validators.py
philo/views.py
philo.egg-info/PKG-INFO
philo.egg-info/SOURCES.txt
philo.egg-info/dependency_links.txt
philo.egg-info/requires.txt
philo.egg-info/top_level.txt
philo/admin/__init__.py
philo/admin/base.py
philo/admin/collections.py
philo/admin/nodes.py
philo/admin/pages.py
philo/admin/widgets.py
philo/admin/forms/__init__.py
philo/admin/forms/attributes.py
philo/admin/forms/containers.py
philo/contrib/__init__.py
philo/contrib/julian/__init__.py
philo/contrib/julian/admin.py
philo/contrib/julian/feedgenerator.py
philo/contrib/julian/models.py
philo/contrib/julian/migrations/0001_initial.py
philo/contrib/julian/migrations/__init__.py
philo/contrib/penfield/__init__.py
philo/contrib/penfield/admin.py
philo/contrib/penfield/models.py
philo/contrib/penfield/migrations/0001_initial.py
philo/contrib/penfield/migrations/0002_auto.py
philo/contrib/penfield/migrations/0003_auto__add_field_newsletterview_feed_type__add_field_newsletterview_ite.py
philo/contrib/penfield/migrations/0004_auto__add_field_newsletterview_feed_length__add_field_blogview_feed_le.py
philo/contrib/penfield/migrations/0005_to_taggit.py
