Metadata-Version: 1.1
Name: philo
Version: 0.9.2
Summary: A foundation for developing web content management systems.
Home-page: http://philocms.org/
Author: iThink Software
Author-email: contact@ithinksw.com
License: ISC License (ISCL)
Platform: OS Independent
Classifier: Environment :: Web Environment
Classifier: Framework :: Django
Classifier: Intended Audience :: Developers
Classifier: License :: OSI Approved :: ISC License (ISCL)
Classifier: Operating System :: OS Independent
Classifier: Programming Language :: Python
Classifier: Topic :: Internet :: WWW/HTTP :: Dynamic Content
Classifier: Topic :: Software Development :: Libraries :: Application Frameworks
